<inputList>
<input name="a"        	     value="Select" />
<input name="b"        	     value="Back" />
<input name="x"        	     value="Stop" />
<input name="y"        	     value="ContextMenu" />
<input name="start"    	     value="PlayPause" />
<input name="select"   	     value="ActivateWindow(10111)" />
<input name="pageup"   	     value="Info" />
<input name="pagedown" 	     value="Queue" />
<input name="l2"       	     value="Mute" />
<input name="r2"       	     value="" />
<input name="up"       	     value="Up" />
<input name="down"     	     value="Down" />
<input name="right"    	     value="Right" />
<input name="left"     	     value="Left" />
<input name="joystick1up"    value="VolumeUp" />
<input name="joystick1down"  value="VolumeDown" />
<input name="joystick1left"  value="VolumeDown" />
<input name="joystick1right" value="VolumeUp" />
<input name="joystick2up"    value="Up" />
<input name="joystick2down"  value="Down" />
<input name="joystick2left"  value="Left" />
<input name="joystick2right" value="Right" />
</inputList>
